optikka_design_data_layer/__init__.py
optikka_design_data_layer/errors.py
optikka_design_data_layer/logger.py
optikka_design_data_layer/ai/__init__.py
optikka_design_data_layer/ai/bedrock_client.py
optikka_design_data_layer/ai/openai_client.py
optikka_design_data_layer/data/__init__.py
optikka_design_data_layer/data/get_asset_data_by_image.py
optikka_design_data_layer/data/validate_brand.py
optikka_design_data_layer/data/validate_template_input_object.py
optikka_design_data_layer/db/__init__.py
optikka_design_data_layer/db/base_postgres_service.py
optikka_design_data_layer/db/connection_types.py
optikka_design_data_layer/db/mongo_client.py
optikka_design_data_layer/db/mongodb_guide_client.py
optikka_design_data_layer/db/postgres_client.py
optikka_design_data_layer/db/postgres_credential_manager.py
optikka_design_data_layer/role_based_logic/__init__.py
optikka_design_data_layer/role_based_logic/role_query_modifier.py
optikka_design_data_layer/utils/__init__.py
optikka_design_data_layer/utils/config.py
optikka_design_data_layer/utils/font_preflight.py
optikka_design_data_layer/utils/response_utils.py
optikka_design_data_layer/utils/s3.py
optikka_design_data_layer/utils/secrets_manager.py
optikka_design_data_layer/validation/__init__.py
optikka_design_data_layer/validation/validate_auth.py
optikka_design_data_layer-0.1.32.dist-info/METADATA
optikka_design_data_layer-0.1.32.dist-info/WHEEL
optikka_design_data_layer-0.1.32.dist-info/top_level.txt
optikka_design_data_layer-0.1.32.dist-info/RECORD
