Metadata-Version: 2.4
Name: optikka-design-data-layer
Version: 0.1.32
Summary: Shared utilities for Optikka microservices (logger, errors, response utils, auth validation, database clients, AI clients)
Author-email: Optikka <dev@optikka.com>
License: PROPRIETARY
Project-URL: Homepage, https://github.com/optikka/ods
Project-URL: Repository, https://github.com/optikka/ods
Keywords: optikka,design,data,layer,aws,lambda
Classifier: Development Status :: 4 - Beta
Classifier: Intended Audience :: Developers
Classifier: Programming Language :: Python :: 3
Classifier: Programming Language :: Python :: 3.11
Classifier: Programming Language :: Python :: 3.12
Classifier: Programming Language :: Python :: 3.13
Requires-Python: >=3.11
Requires-Dist: boto3<2.0.0,>=1.34.0
Requires-Dist: pydantic<3.0.0,>=2.6.1
Requires-Dist: PyJWT<3.0.0,>=2.10.1
Requires-Dist: aws-lambda-powertools<3.0.0,>=2.32.0
Requires-Dist: psycopg2-binary<3.0.0,>=2.9.10
Requires-Dist: pymongo<5.0.0,>=4.13.0
Requires-Dist: requests<3.0.0,>=2.32.3
Requires-Dist: openai<2.0.0,>=1.61.0
Requires-Dist: cryptography>=3.4.0
Requires-Dist: ods-models-py<1.0.0,>=0.1.19
Requires-Dist: ods-types-py<1.0.0,>=0.1.5
Provides-Extra: dev
Requires-Dist: pytest>=7.4.0; extra == "dev"
Requires-Dist: pytest-cov>=4.1.0; extra == "dev"
Requires-Dist: black>=23.0.0; extra == "dev"
Requires-Dist: ruff>=0.1.0; extra == "dev"
Requires-Dist: mypy>=1.5.0; extra == "dev"
